{"id": 367, "name": "Clay Soldiers", "slot": "2nd Ability", "icon": "https://gamepedia.cursecdn.com/smite_gamepedia/b/b7/Icons_NuWa_A02.png", "ability_type": "Pet", "description": "Nu Wa conjures Clay Soldiers from the earth. If she marked a target while summoning them, they will pursue that target until it dies. If she summons them without target, they will attack enemy gods who damage Nu Wa, or closest enemies.\nSoldiers live for 10s. First they will dash at enemies within 45 units, applying a stack of protection reduction. Stacks up to 3 times, stacks last 2s. They will basic attack after that.", "stats": ["Number Conjured: 1/2/2/2/3 Soldiers", "Soldier's Health: 200 (+20% of your maximum health)", "Dash Magical Protection Reduction Per Stack: 4/8/12/16/20", "Basic Attack Damage: 20/30/40/50/60 Per Hit", "Range: 40", "Cooldown: 16 seconds", "Cost: 60/70/80/90/100 mana"], "god": {"name": "Nu Wa", "url": "https://smiteapi.adammackle.com/gods/73"}}