{"id": 411, "name": "Astral Strike", "slot": "1st Ability", "icon": "https://gamepedia.cursecdn.com/smite_gamepedia/a/a8/Icons_Ram_A01.png", "ability_type": "Buff", "description": "Rama switches to a more powerful arrow that pierces and slows enemies. This ability consumes 1 of Rama's Astral Arrows and deals bonus damage with every shot. Damage from this ability is reduced to 75% for each enemy hit after the first. Rama cannot toggle this ability if he has no Astral Arrows.\nThe slow can be stacked up to 3 times.", "stats": ["Slow\u00a0%: 10%", "Time Slowed: 2s", "Bonus Damage: 10/20/30/40/50", "Cost: 20 mana + 1 arrow per shot"], "god": {"name": "Rama", "url": "https://smiteapi.adammackle.com/gods/82"}}