{"id": 74, "name": "Shield Wall", "slot": "3rd Ability", "icon": "https://gamepedia.cursecdn.com/smite_gamepedia/8/82/Icons_Athena_A03.png", "ability_type": "Ground", "description": "Athena summons a group of Athenian warriors who do damage upon arrival, and after 2s strike for additional damage.", "stats": ["Initial Damage: 70/110/150/190/230 (+50% of your magical power)", "Secondary Damage: 70/135/200/265/330 (+50% of your magical power)", "Radius: 15", "Cooldown: 14 seconds", "Cost: 60/65/70/75/80 mana"], "god": {"name": "Athena", "url": "https://smiteapi.adammackle.com/gods/15"}}