{"Abilities": [{"PutRequest": {"Item": {"ID": {"S": "256"}, "Name": {"S": "Death Draws Nigh"}, "Description": {"S": "The closer Izanami gets to death, the more powerful she becomes. Izanami gains 4% Physical Penetration for each 10% of her Health that is missing, up to a maximum of 20%.Also, Izanami's Basic Attacks only trigger Item effects on the first target hit per attack"}, "Slot": {"S": "Passive"}, "Picture": {"S": "https://gamepedia.cursecdn.com/smite_gamepedia/f/f0/Icons_Izanami_Passive.png"}, "God": {"M": {"ID": {"S": "52"}, "URL": {"S": "https://smiteapi.adammackle.com/god/52"}}}}}}]}