{"Abilities": [{"PutRequest": {"Item": {"ID": {"S": "236"}, "Name": {"S": "Resolute"}, "Description": {"S": "Each time Horus is damaged by an enemy god, Horus gains a stack of Resolute. If Set is the god damaging Horus, Horus gains 2 stacks. Each stack increases Horus' Protections and CCR. Resolute stacks to a max count of 10 for 3s. When Resolute fades, Horus is healed based on the amount of stacks."}, "Slot": {"S": "Passive"}, "Picture": {"S": "https://gamepedia.cursecdn.com/smite_gamepedia/5/54/Icons_Horus_Passive.png"}, "God": {"M": {"ID": {"S": "48"}, "URL": {"S": "https://smiteapi.adammackle.com/god/48"}}}}}}]}