{"Abilities": [{"PutRequest": {"Item": {"ID": {"S": "320"}, "Name": {"S": "Sonic Boom"}, "Description": {"S": "Mercury gathers energy for a powerful dash, with the range extending as he does so. He travels the distance faster than the speed of sound, dealing damage to all enemies, stunning them and spinning them around in a random direction."}, "Slot": {"S": "Ultimate"}, "Picture": {"S": "https://gamepedia.cursecdn.com/smite_gamepedia/2/23/Icons_Mercury_A04.png"}, "God": {"M": {"ID": {"S": "64"}, "URL": {"S": "https://smiteapi.adammackle.com/god/64"}}}}}}]}