{"Abilities": [{"PutRequest": {"Item": {"ID": {"S": "199"}, "Name": {"S": "Stone Shield"}, "Description": {"S": "Geb targets himself or an ally to put a Shield around. The Shield blocks all damage and lasts until its time expires or it takes enough damage to be destroyed. The Shield also cleanses any CC when applied."}, "Slot": {"S": "3rd Ability"}, "Picture": {"S": "https://gamepedia.cursecdn.com/smite_gamepedia/c/cd/Icons_Geb_A02.png"}, "God": {"M": {"ID": {"S": "40"}, "URL": {"S": "https://smiteapi.adammackle.com/god/40"}}}}}}]}