{"Abilities": [{"PutRequest": {"Item": {"ID": {"S": "335"}, "Name": {"S": "World Weaver"}, "Description": {"S": "Neith charges up and fires an arrow across the world, seeking its target through obstacles. Enemy gods take damage and are stunned. The arrow can be fired quicker for diminished results."}, "Slot": {"S": "Ultimate"}, "Picture": {"S": "https://gamepedia.cursecdn.com/smite_gamepedia/4/4c/Icons_Neith_A04.png"}, "God": {"M": {"ID": {"S": "67"}, "URL": {"S": "https://smiteapi.adammackle.com/god/67"}}}}}}]}